LICENSE
virttop/virttop.py
virttop-0.2.4.dist-info/LICENSE
virttop-0.2.4.dist-info/METADATA
virttop-0.2.4.dist-info/WHEEL
virttop-0.2.4.dist-info/entry_points.txt
virttop-0.2.4.dist-info/RECORD
